LICENSE.txt
MANIFEST.in
README.txt
argonaut.sqlite
development.ini
ez_setup.py
setup.cfg
setup.py
test.ini
Argonaut.egg-info/PKG-INFO
Argonaut.egg-info/SOURCES.txt
Argonaut.egg-info/dependency_links.txt
Argonaut.egg-info/entry_points.txt
Argonaut.egg-info/not-zip-safe
Argonaut.egg-info/paster_plugins.txt
Argonaut.egg-info/requires.txt
Argonaut.egg-info/top_level.txt
argonaut/__init__.py
argonaut/websetup.py
argonaut/config/__init__.py
argonaut/config/deployment.ini_tmpl
argonaut/config/environment.py
argonaut/config/middleware.py
argonaut/config/routing.py
argonaut/controllers/__init__.py
argonaut/controllers/account.py
argonaut/controllers/admin.py
argonaut/controllers/blog.py
argonaut/controllers/comment.py
argonaut/controllers/error.py
argonaut/controllers/feed.py
argonaut/controllers/landing.py
argonaut/controllers/page.py
argonaut/controllers/tag.py
argonaut/lib/__init__.py
argonaut/lib/app_globals.py
argonaut/lib/authentication.py
argonaut/lib/base.py
argonaut/lib/helpers.py
argonaut/lib/mailer.py
argonaut/lib/timehelpers.py
argonaut/lib/version.py
argonaut/model/__init__.py
argonaut/model/auth.py
argonaut/model/box.py
argonaut/model/boxes.py
argonaut/model/comment.py
argonaut/model/config.py
argonaut/model/forms.py
argonaut/model/media.py
argonaut/model/meta.py
argonaut/model/page.py
argonaut/model/page_type.py
argonaut/model/post.py
argonaut/model/social.py
argonaut/model/tag.py
argonaut/model/tag_post.py
argonaut/model/initial_data/__init__.py
argonaut/model/initial_data/auth_data.py
argonaut/model/initial_data/box_data.py
argonaut/model/initial_data/boxes_data.py
argonaut/model/initial_data/config_data.py
argonaut/model/initial_data/media_data.py
argonaut/model/initial_data/page_data.py
argonaut/model/initial_data/page_type_data.py
argonaut/model/initial_data/social_data.py
argonaut/public/favicon.ico
argonaut/public/site_logo.gif
argonaut/public/ckeditor/CHANGES.html
argonaut/public/ckeditor/INSTALL.html
argonaut/public/ckeditor/LICENSE.html
argonaut/public/ckeditor/ckeditor.asp
argonaut/public/ckeditor/ckeditor.js
argonaut/public/ckeditor/ckeditor.pack
argonaut/public/ckeditor/ckeditor.php
argonaut/public/ckeditor/ckeditor_basic.js
argonaut/public/ckeditor/ckeditor_basic_source.js
