Metadata-Version: 1.0
Name: Argonaut
Version: 0.3.4
Summary: Lightweight Pylons powered blogging engine.
Home-page: http://www.basshero.org
Author: Jason Robinson
Author-email: jaywink@basshero.org
License: FreeBSD
Download-URL: http://pypi.python.org/pypi/Argonaut
Keywords: python pylons blogging cms blog
Platform: UNKNOWN
Classifier: Development Status :: 3 - Alpha
Classifier: License :: OSI Approved :: BSD License
Classifier: Environment :: Web Environment
Classifier: Framework :: Pylons
Classifier: Framework :: Paste
Classifier: Intended Audience :: Developers
Classifier: Natural Language :: English
Classifier: Operating System :: OS Independent
Classifier: Programming Language :: Python
Classifier: Programming Language :: Python :: 2.4
Classifier: Programming Language :: Python :: 2.5
Classifier: Programming Language :: Python :: 2.6
Classifier: Topic :: Internet :: WWW/HTTP :: Site Management
Classifier: Topic :: Internet :: WWW/HTTP
Classifier: Topic :: Internet :: WWW/HTTP :: Dynamic Content
Classifier: Topic :: Internet :: WWW/HTTP :: WSGI
